yta_video_opencv/__init__.py
yta_video_opencv/canvas.py
yta_video_opencv/frame/__init__.py
yta_video_opencv/frame/effects.py
yta_video_opencv/reader.py
yta_video_opencv/remove_this_code.py
yta_video_opencv/render.py
yta_video_opencv/utils.py
yta_video_opencv/writer.py
yta_video_opencv-0.0.7.dist-info/LICENSE
yta_video_opencv-0.0.7.dist-info/METADATA
yta_video_opencv-0.0.7.dist-info/WHEEL
yta_video_opencv-0.0.7.dist-info/RECORD
