Metadata-Version: 2.3
Name: yta-video-opencv
Version: 0.0.7
Summary: Youtube Autonomous Video OpenCV Module
Author: danialcala94
Author-email: danielalcalavalera@gmail.com
Requires-Python: ==3.9
Classifier: Programming Language :: Python :: 3
Classifier: Programming Language :: Python :: 3.9
Requires-Dist: numpy (>=0.0.1,<9.0.0)
Requires-Dist: opencv-python (>=0.0.1,<9.0.0)
Requires-Dist: yta_colors (>=0.0.1,<1.0.0)
Requires-Dist: yta_constants (>=0.0.1,<1.0.0)
Requires-Dist: yta_general_utils (>=0.0.1,<1.0.0)
Requires-Dist: yta_random (>=0.0.1,<1.0.0)
Requires-Dist: yta_timer (>=0.0.1,<1.0.0)
Requires-Dist: yta_validation (>=0.0.1,<1.0.0)
Requires-Dist: yta_video_frame_time (>=0.0.1,<1.0.0)
